plib/ui/__init__.py
plib/ui/app.py
plib/ui/coll.py
plib/ui/common.py
plib/ui/custom.py
plib/ui/defs.py
plib/ui/dialogs.py
plib/ui/examples.py
plib/ui/fileaware.py
plib/ui/imp.py
plib/ui/manager.py
plib/ui/output.py
plib/ui/prefs.py
plib/ui/socket.py
plib/ui/textfile.py
plib/ui/widgets.py
plib/ui/base/__init__.py
plib/ui/base/app.py
plib/ui/base/button.py
plib/ui/base/combo.py
plib/ui/base/container.py
plib/ui/base/dialog.py
plib/ui/base/display.py
plib/ui/base/editctrl.py
plib/ui/base/focus.py
plib/ui/base/form.py
plib/ui/base/group.py
plib/ui/base/groupbox.py
plib/ui/base/helpers.py
plib/ui/base/html.py
plib/ui/base/imageview.py
plib/ui/base/label.py
plib/ui/base/listbox.py
plib/ui/base/listview.py
plib/ui/base/mainwin.py
plib/ui/base/mouse.py
plib/ui/base/pagewidget.py
plib/ui/base/scroller.py
plib/ui/base/socket.py
plib/ui/base/table.py
plib/ui/base/tabwidget.py
plib/ui/images/about-darwin.png
plib/ui/images/about-gtk.png
plib/ui/images/about-posix.png
plib/ui/images/about-pyside.png
plib/ui/images/about-pyside2.png
plib/ui/images/about-qt4.png
plib/ui/images/about-qt5.png
plib/ui/images/about-win32.png
plib/ui/images/about-wx.png
plib/ui/images/about_toolkit-gtk.png
plib/ui/images/about_toolkit-kde.png
plib/ui/images/about_toolkit-kde4.png
plib/ui/images/about_toolkit-pyside.png
plib/ui/images/about_toolkit-pyside2.png
plib/ui/images/about_toolkit-qt.png
plib/ui/images/about_toolkit-qt4.png
plib/ui/images/about_toolkit-qt5.png
plib/ui/images/about_toolkit-wx.png
plib/ui/images/add-darwin.png
plib/ui/images/add-gtk.png
plib/ui/images/add-posix.png
plib/ui/images/add-pyside.png
plib/ui/images/add-pyside2.png
plib/ui/images/add-qt4.png
plib/ui/images/add-wx.png
plib/ui/images/apply-gtk.png
plib/ui/images/apply-kde4.png
plib/ui/images/apply-posix.png
plib/ui/images/apply-pyside.png
plib/ui/images/apply-pyside2.png
plib/ui/images/apply-qt4.png
plib/ui/images/apply-wx.png
plib/ui/images/cancel-darwin.png
plib/ui/images/cancel-gtk.png
plib/ui/images/cancel-kde4.png
plib3.ui-0.18.dist-info/LICENSE.txt
plib3.ui-0.18.dist-info/METADATA
plib3.ui-0.18.dist-info/WHEEL
plib3.ui-0.18.dist-info/entry_points.txt
plib3.ui-0.18.dist-info/top_level.txt
plib3.ui-0.18.dist-info/RECORD
